[
  {
    "id": "kн-131-2026-y-к-k-160-130",
    "path": "./kн-131-2026-y-к-k-160-130/document.json",
    "code": "KH 205-131:2023",
    "title": "_______________________________________________________________________________________",
    "sourceLanguage": "uzLatn"
  },
  {
    "id": "kн-132-2023-лотинча-февраль-2025-doc",
    "path": "./kн-132-2023-лотинча-февраль-2025-doc/document.json",
    "code": "KН 132-2023 лотинча февраль 2025 - doc.",
    "title": "TGM-94 QOZONIDA AVARIYALARNING",
    "sourceLanguage": "uzLatn"
  },
  {
    "id": "kн-145-2025-лотин-февраль-2025",
    "path": "./kн-145-2025-лотин-февраль-2025/document.json",
    "code": "KH 205-145:2025",
    "title": "0,0 m. BELGIDA JOYLASHGAN TURBINA USKUNALARINI",
    "sourceLanguage": "uzLatn"
  },
  {
    "id": "kн-205-138-2025-лотин-февраль-2025",
    "path": "./kн-205-138-2025-лотин-февраль-2025/document.json",
    "code": "KH 205-138:2025",
    "title": "K-160-130 RUSUMLI BUG‘ TURBINANING ROSTLASH TIZIMINI ISHLATISH VA TAVSIFLAB BERISH YO‘RIQNOMASI",
    "sourceLanguage": "uzLatn"
  },
  {
    "id": "kн-205-140-2025-лотин-февраль-2025",
    "path": "./kн-205-140-2025-лотин-февраль-2025/document.json",
    "code": "KН 205-140:2025",
    "title": "___________________________________________________________________________________________",
    "sourceLanguage": "uzLatn"
  },
  {
    "id": "вакуумная_сушка_поверхн_нагрева_и_п_п_котла",
    "path": "./вакуумная_сушка_поверхн_нагрева_и_п_п_котла/document.json",
    "code": "Вакуумная_сушка_поверхн_нагрева_и_п_п_котла",
    "title": "АО « Ташкентская ТЭС»",
    "sourceLanguage": "ru"
  },
  {
    "id": "кн-143-2026-и-лотин",
    "path": "./кн-143-2026-и-лотин/document.json",
    "code": "KН 205-143:2026",
    "title": "TGM-94 BARABANLI QOZON BILAN BLOKDA ISHLOVCHI K-160-130 VA PVK-150 RUSUMLI BUG’ TURBINASINI ISHLATISH YO’RIQNOMASI",
    "sourceLanguage": "uzLatn"
  },
  {
    "id": "останов_турбиннои-_установки_no8_в_режим_холост_ход",
    "path": "./останов_турбиннои-_установки_no8_в_режим_холост_ход/document.json",
    "code": "Останов_турбинной_установки_№8_в_режим_холост_ход",
    "title": "ОСТАНОВ ТУРБИННОЙ УСТАНОВКИ",
    "sourceLanguage": "ru"
  },
  {
    "id": "ппр-восстановл-хим-режима-2026-г",
    "path": "./ппр-восстановл-хим-режима-2026-г/document.json",
    "code": "х 280",
    "title": "ЭТА ПРОГРАММА НЕ НУЖНА",
    "sourceLanguage": "ru"
  },
  {
    "id": "ппрограмма_восстановления_хим_режима",
    "path": "./ппрограмма_восстановления_хим_режима/document.json",
    "code": "Ппрограмма_восстановления_ХИМ_РЕЖИМА",
    "title": "Производства работ по восстановлению химического режима на блоке.",
    "sourceLanguage": "ru"
  },
  {
    "id": "ппрограмма_восстановления_хим_режима_10_блока",
    "path": "./ппрограмма_восстановления_хим_режима_10_блока/document.json",
    "code": "Ппрограмма_восстановления_ХИМ_РЕЖИМА_10_БЛОКА",
    "title": "Производства работ по восстановлению химического режима на блоке.",
    "sourceLanguage": "ru"
  },
  {
    "id": "проверка_плотности_стоп_и_рег_клап_тг_2025",
    "path": "./проверка_плотности_стоп_и_рег_клап_тг_2025/document.json",
    "code": "Проверка_плотности_стоп_и_рег_клап_ТГ_2025",
    "title": "АО « ТАШКЕНТСКАЯ ТЭС»",
    "sourceLanguage": "ru"
  },
  {
    "id": "проверка_плотности_стоп_и_рег_клап_тг_2026",
    "path": "./проверка_плотности_стоп_и_рег_клап_тг_2026/document.json",
    "code": "Проверка_плотности_стоп_и_рег_клап_ТГ_2026",
    "title": "АО « ТАШКЕНТСКАЯ ТЭС»",
    "sourceLanguage": "ru"
  },
  {
    "id": "программа_гидравлич_испытание_бл_2026",
    "path": "./программа_гидравлич_испытание_бл_2026/document.json",
    "code": "Программа_гидравлич_испытание_бл_2026",
    "title": "АО « ТАШКЕНТСКАЯ ТЭС»",
    "sourceLanguage": "ru"
  },
  {
    "id": "программа_паровои-_продувки_котла_no1_новая_уэт_2024",
    "path": "./программа_паровои-_продувки_котла_no1_новая_уэт_2024/document.json",
    "code": "Программа_паровой_продувки_котла_№1_новая_УЭТ_2024",
    "title": "Программа паровой продувки котла",
    "sourceLanguage": "ru"
  },
  {
    "id": "программа_паровои-_продувки_котла_no1_новая_уэт_2024_образец",
    "path": "./программа_паровои-_продувки_котла_no1_новая_уэт_2024_образец/document.json",
    "code": "Программа_паровой_продувки_котла_№1_новая_УЭТ_2024_образец_",
    "title": "Программа паровой продувки котла",
    "sourceLanguage": "ru"
  },
  {
    "id": "программа_пуск_турб_из_холодн_сост",
    "path": "./программа_пуск_турб_из_холодн_сост/document.json",
    "code": "х 5",
    "title": "пуск блока из холодного состояния ТГ после ремонта.",
    "sourceLanguage": "ru"
  },
  {
    "id": "вывод-бл-в-кап-и-ср-рем-2026",
    "path": "./вывод-бл-в-кап-и-ср-рем-2026/document.json",
    "code": "вывод бл.в кап. и ср. рем. 2026",
    "title": "вывод энергоблоков в капитальные и средние ремонты энергоблоков Таш ТЭС.",
    "sourceLanguage": "ru"
  },
  {
    "id": "гидравлич-испытание-бл-2025",
    "path": "./гидравлич-испытание-бл-2025/document.json",
    "code": "гидравлич. испытание бл. 2025",
    "title": "АО « ТАШКЕНТСКАЯ ТЭС»",
    "sourceLanguage": "ru"
  },
  {
    "id": "опроб-защиты-от-разгона-2025",
    "path": "./опроб-защиты-от-разгона-2025/document.json",
    "code": "опроб.защиты от разгона - 2025",
    "title": "АО « ТАШКЕНТСКАЯ ТЭС»",
    "sourceLanguage": "ru"
  },
  {
    "id": "опроб-защиты-от-разгона-2026",
    "path": "./опроб-защиты-от-разгона-2026/document.json",
    "code": "опроб.защиты от разгона - 2026",
    "title": "АО « ТАШКЕНТСКАЯ ТЭС»",
    "sourceLanguage": "ru"
  },
  {
    "id": "очистка-маслосистемы-2025",
    "path": "./очистка-маслосистемы-2025/document.json",
    "code": "очистка маслосистемы  2025",
    "title": "АО « ТАШКЕНТСКАЯ ТЭС»",
    "sourceLanguage": "ru"
  },
  {
    "id": "пар-опроб-и-пуск-на-хол-ход-2025",
    "path": "./пар-опроб-и-пуск-на-хол-ход-2025/document.json",
    "code": "пар. опроб. и пуск на хол.ход-2025",
    "title": "АО « ТАШКЕНТСКАЯ ТЭС»",
    "sourceLanguage": "ru"
  },
  {
    "id": "перевод-сар-2026",
    "path": "./перевод-сар-2026/document.json",
    "code": "перевод САР 2026",
    "title": "АО « ТАШКЕНТСКАЯ ТЭС»",
    "sourceLanguage": "ru"
  },
  {
    "id": "пров-опрес-первичн-тракта-2026",
    "path": "./пров-опрес-первичн-тракта-2026/document.json",
    "code": "пров.опрес.первичн.тракта 2026",
    "title": "АО « Ташкентская ТЭС»",
    "sourceLanguage": "ru"
  },
  {
    "id": "проверка_работоспособности_пр_кл_ипу_2-хпп_2026",
    "path": "./проверка_работоспособности_пр_кл_ипу_2-хпп_2026/document.json",
    "code": "проверка_работоспособности_пр_кл_ИПУ_2,ХПП_2026",
    "title": "АО « Ташкентская ТЭС»",
    "sourceLanguage": "ru"
  },
  {
    "id": "прог_проведения_настрои-ки_ипу_2026",
    "path": "./прог_проведения_настрои-ки_ипу_2026/document.json",
    "code": "прог_проведения_настройки_ИПУ_2026",
    "title": "проведения настройки импульсных предохранительных устройств котла",
    "sourceLanguage": "ru"
  },
  {
    "id": "продувка-паропров-после-рем-2025",
    "path": "./продувка-паропров-после-рем-2025/document.json",
    "code": "продувка паропров. после рем - 2025",
    "title": "АО « ТАШКЕНТСКАЯ ТЭС»",
    "sourceLanguage": "ru"
  },
  {
    "id": "продувка-паропров-после-рем-2026",
    "path": "./продувка-паропров-после-рем-2026/document.json",
    "code": "продувка паропров. после рем - 2026",
    "title": "АО « ТАШКЕНТСКАЯ ТЭС»",
    "sourceLanguage": "ru"
  },
  {
    "id": "пуск_на_холостои-_ход_и_пров_авт_безопасн_2026",
    "path": "./пуск_на_холостои-_ход_и_пров_авт_безопасн_2026/document.json",
    "code": "пуск_на_холостой_ход_и_пров_авт_безопасн_2026",
    "title": "АО « ТАШКЕНТСКАЯ ТЭС»",
    "sourceLanguage": "ru"
  },
  {
    "id": "хим_очистка_экран_труб_котла_солян_кислотои-_2026",
    "path": "./хим_очистка_экран_труб_котла_солян_кислотои-_2026/document.json",
    "code": "хим_очистка_экран_труб_котла_солян_кислотой_2026",
    "title": "Химической очистки экранных труб котла № соляной кислотной.",
    "sourceLanguage": "ru"
  }
]